README.md
setup.py
vgelectricity.py
vg_electricity.egg-info/PKG-INFO
vg_electricity.egg-info/SOURCES.txt
vg_electricity.egg-info/dependency_links.txt
vg_electricity.egg-info/requires.txt
vg_electricity.egg-info/top_level.txt